td2inner/__init__.py
td2inner/fractionals.pxd
td2inner/fractionals.pyx
td2inner/setupfractionals.py
td2inner/td2inner.py
td2inner-1.0.0.4.dist-info/METADATA
td2inner-1.0.0.4.dist-info/WHEEL
td2inner-1.0.0.4.dist-info/licenses/LICENSE
td2inner-1.0.0.4.dist-info/RECORD
